hyperion/__init__.py
hyperion_logs-0.0.4.dist-info/DESCRIPTION.rst
hyperion_logs-0.0.4.dist-info/METADATA
hyperion_logs-0.0.4.dist-info/RECORD
hyperion_logs-0.0.4.dist-info/WHEEL
hyperion_logs-0.0.4.dist-info/metadata.json
hyperion_logs-0.0.4.dist-info/top_level.txt
