Metadata-Version: 2.0
Name: hyperion-logs
Version: 0.0.4
Summary: UNKNOWN
Home-page: UNKNOWN
Author: Scott Snyder
Author-email: scott.snyder@capitalone.com
License: Creative Commons Attribution-Noncommercial-Share Alike license
Platform: UNKNOWN
